webshart-0.4.3.dist-info/METADATA
webshart-0.4.3.dist-info/WHEEL
webshart-0.4.3.dist-info/entry_points.txt
webshart-0.4.3.dist-info/licenses/LICENSE
webshart/__init__.py
webshart/_webshart.cpython-313-darwin.so
webshart/cache_wait.py
webshart-0.4.3.dist-info/RECORD
