Metadata-Version: 2.4
Name: webshart
Version: 0.4.3
Classifier: Development Status :: 3 - Alpha
Classifier: Intended Audience :: Developers
Classifier: License :: OSI Approved :: MIT License
Classifier: License :: OSI Approved :: Apache Software License
Classifier: Programming Language :: Python :: 3
Classifier: Programming Language :: Python :: 3.8
Classifier: Programming Language :: Python :: 3.9
Classifier: Programming Language :: Python :: 3.10
Classifier: Programming Language :: Python :: 3.11
Classifier: Programming Language :: Python :: 3.12
Classifier: Programming Language :: Rust
Classifier: Topic :: Software Development :: Libraries :: Python Modules
Requires-Dist: tqdm>=4.67.1,<5.0.0
License-File: LICENSE
Summary: Fast and memory-efficient webdataset shard reader
Keywords: dataset,shards,tar,webdataset,machine-learning
Author-email: bghira <bghira@users.github.com>
License: MIT
Requires-Python: >=3.8
Project-URL: Homepage, https://github.com/bghira/webshart
Project-URL: Repository, https://github.com/bghira/webshart
Project-URL: Issues, https://github.com/bghira/webshart/issues
